{
  "level_id": "invest_discipline_01",
  "title": "回撤中的仓位考验",
  "intro": "你管理个人投资账户，年初制定了“最大回撤15%止损、单一标的不超25%仓位”的纪律。三个月前你以36元买入“星河半导体”，目前跌至24.5元，社群里有人说“再跌就是送”，也有人喊“反弹到30就走”。同时，一只你早就关注的“远景医药”出现放量突破，但你可用资金不多。你需要做出抉择。",
  "target_model": "投资纪律",
  "victory_condition": "遵守既定投资计划与风控纪律，避免情绪化交易并保护本金。",
  "max_turns": 8,
  "challenge_limit": 3,
  "model_explanation": {
    "definition": "投资纪律指在入场前制定规则，并在波动中按规则执行，避免被情绪与噪音驱动。它强调过程一致性与风险控制。",
    "example": "当持仓超过止损线时，纪律要求你按计划减仓或止损，而不是因为“已经跌很多”就继续补仓。",
    "pitfall": "常见误区包括随意调整止损线、被群体情绪带节奏、亏损时盲目加码摊平。",
    "advice": "在入场前明确仓位、止损、退出条件；在波动中只按规则执行，不被短期消息改变策略。",
    "triggers": [
      "标的短期大幅回撤",
      "市场噪音与群体情绪影响判断",
      "出现新机会但资金有限"
    ],
    "steps": [
      "回看交易计划与风险规则",
      "对照当前持仓与止损条件",
      "按规则执行调整或退出",
      "评估新机会是否符合既定策略"
    ],
    "success_signals": [
      "决策依据清晰可追溯",
      "仓位与止损严格遵守",
      "避免情绪化追涨杀跌"
    ]
  },
  "setting": "个人投资账户，市场波动加剧，社群噪音强，需坚持计划与风控。"
}
